sectioner.libs/libgcc_s-1e52349c.so.1
sectioner/__init__.py
sectioner/sectioner.abi3.so
tilt_sectioner-0.1.2.dist-info/METADATA
tilt_sectioner-0.1.2.dist-info/WHEEL
tilt_sectioner-0.1.2.dist-info/licenses/LICENSE
tilt_sectioner-0.1.2.dist-info/RECORD
