Metadata-Version: 2.4
Name: tilt-sectioner
Version: 0.1.2
Classifier: Programming Language :: Rust
Classifier: Programming Language :: Python :: Implementation :: CPython
Classifier: Programming Language :: Python :: Implementation :: PyPy
License-File: LICENSE
Summary: Source data sectioner for Tilt Networks
Author-email: Paulo Moreira <paulo@tilt.technology>
Requires-Python: >=3.8
